tests/__init__.py
tests/test_users.py
user_data/__init__.py
user_data/info.py
user_data/permissions.py
user_data/settings.py
user_data/util.py
user_data-0.1.0.dist-info/LICENSE
user_data-0.1.0.dist-info/METADATA
user_data-0.1.0.dist-info/WHEEL
user_data-0.1.0.dist-info/top_level.txt
user_data-0.1.0.dist-info/RECORD
