Metadata-Version: 2.1
Name: user-data
Version: 0.1.0
Summary: A package for managing user information and settings on Windows systems.
Home-page: https://github.com/aidmet/user_data
Author: Aiden Metcalfe
Author-email: avaartshop@outlook.com
Classifier: Programming Language :: Python :: 3
Classifier: License :: OSI Approved :: MIT License
Classifier: Operating System :: OS Independent
Requires-Python: >=3.11
License-File: LICENSE
